LICENSE
MANIFEST.in
README.rst
setup.py
amazon_payments/__init__.py
amazon_payments/api.py
amazon_payments/models.py
amazon_payments/urls.py
amazon_payments/views.py
amazon_payments/migrations/0001_initial.py
amazon_payments/migrations/__init__.py
amazon_payments/templates/amazon_payments/onestep_checkout.html
amazon_payments/templates/amazon_payments/payment_details.html
amazon_payments/templates/amazon_payments/preview.html
amazon_payments/templates/amazon_payments/shipping_address.html
django_oscar_amazon_payments.egg-info/PKG-INFO
django_oscar_amazon_payments.egg-info/SOURCES.txt
django_oscar_amazon_payments.egg-info/dependency_links.txt
django_oscar_amazon_payments.egg-info/requires.txt
django_oscar_amazon_payments.egg-info/top_level.txt