Metadata-Version: 1.1
Name: django-oscar-amazon-payments
Version: 0.1
Summary: This package provides integration between django-oscar and Amazon Payments (Login and Pay with Amazon).
Home-page: https://github.com/simonkagwe/django-oscar-amazon-payments
Author: Simon Kagwi
Author-email: simonkagwe@yahoo.com
License: The MIT License (MIT)
